mantlebio/__init__.py
mantlebio/client.py
mantlebio/exceptions.py
mantlebio/core/__init__.py
mantlebio/core/constants.py
mantlebio/core/analysis/__init__.py
mantlebio/core/analysis/client.py
mantlebio/core/analysis/helpers.py
mantlebio/core/analysis/mantle_analysis.py
mantlebio/core/analysis/tests/__init__.py
mantlebio/core/analysis/tests/test_client.py
mantlebio/core/analysis/tests/test_helpers.py
mantlebio/core/analysis/tests/test_mantle_analysis.py
mantlebio/core/auth/__init__.py
mantlebio/core/auth/creds.py
mantlebio/core/auth/mantle_auth.py
mantlebio/core/auth/tests/__init__.py
mantlebio/core/auth/tests/test_auth.py
mantlebio/core/dataset/__init__.py
mantlebio/core/dataset/client.py
mantlebio/core/dataset/helpers.py
mantlebio/core/dataset/mantle_dataset.py
mantlebio/core/dataset/tests/__init__.py
mantlebio/core/dataset/tests/test_client.py
mantlebio/core/dataset/tests/test_helpers.py
mantlebio/core/dataset/tests/test_mantle_dataset.py
mantlebio/core/pipeline/__init__.py
mantlebio/core/pipeline/client.py
mantlebio/core/pipeline/mantle_pipeline.py
mantlebio/core/pipeline/tests/__init__.py
mantlebio/core/pipeline/tests/test_client.py
mantlebio/core/pipeline_run/__init__.py
mantlebio/core/pipeline_run/client.py
mantlebio/core/pipeline_run/helpers.py
mantlebio/core/pipeline_run/mantle_pipeline_run.py
mantlebio/core/session/__init__.py
mantlebio/core/session/helpers.py
mantlebio/core/session/mantle_session.py
mantlebio/core/session/tests/__init__.py
mantlebio/core/session/tests/test_helpers.py
mantlebio/core/session/tests/test_session.py
mantlebio/core/storage/__init__.py
mantlebio/core/storage/client.py
mantlebio/core/storage/tests/__init__.py
mantlebio/core/storage/tests/test_client.py
mantlebio/helpers/__init__.py
mantlebio/helpers/decorators.py
mantlebio/tests/__init__.py
mantlebio/tests/helpers.py
mantlebio/tests/test_client.py
mantlebio/types/__init__.py
mantlebio/types/query/__init__.py
mantlebio/types/query/query_builder.py
mantlebio-2.1.1.dist-info/LICENSE
mantlebio-2.1.1.dist-info/METADATA
mantlebio-2.1.1.dist-info/WHEEL
mantlebio-2.1.1.dist-info/top_level.txt
mantlebio-2.1.1.dist-info/RECORD
