Metadata-Version: 2.1
Name: mantlebio
Version: 2.1.1
Summary: MantleBio Python SDK
Author: MantleBio
License-File: LICENSE
Requires-Dist: requests >=2.26.0
Requires-Dist: boto3 >=1.34.45
Requires-Dist: botocore >=1.34.45
Requires-Dist: python-dotenv >0.19.2
Requires-Dist: protobuf >=5.00.0
Requires-Dist: google-auth >=2.6.6
Requires-Dist: python-dotenv
Requires-Dist: pandas >=2.0.3
Requires-Dist: numpy <1.29.0,>=1.22.4
